<?xml version="1.0" encoding="UTF-8"?><!DOCTYPE mapper  PUBLIC "-//mybatis.org//DTD Mapper 3.0//EN"  "http://mybatis.org/dtd/mybatis-3-mapper.dtd"><mapper namespace="com.yskj.dao.DocumentDao" ><!-- 查询字段 --><sql id="columnList" >	d.id,	 d.focumentImg, d.resumeID, d.effective, d.documentName, d.createTime, d.updateTime, d.version, d.isDeleted, d.createBy, d.updateBy</sql><!--通过id集合in查询--><sql id="inClause">    <if test="column!=null">        <if test="ids==null">            and 1=0        </if>        <if test="ids!=null">            <if test="ids.size>0">                and  d.${column} in                <foreach item="items" index="index" collection="ids" open="(" separator="," close=")">                    #{items}                </foreach>            </if>            <if test="ids.size==0">                and 1=0            </if>        </if>    </if></sql><!-- 查询条件 --><sql id="whereClause">where 1=1<trim  suffixOverrides="," >	<if test="condition.id != null" >	    and d.id = #{condition.id}	</if>	<if test="condition.focumentImg != null" >and  d.focumentImg = #{condition.focumentImg}</if><if test="condition.resumeID != null" >and  d.resumeID = #{condition.resumeID}</if><if test="condition.effective != null" >and  d.effective = #{condition.effective}</if><if test="condition.documentName != null" >and  d.documentName = #{condition.documentName}</if><if test="condition.createTime != null" >and  d.createTime = #{condition.createTime}</if><if test="condition.updateTime != null" >and  d.updateTime = #{condition.updateTime}</if><if test="condition.version != null" >and  d.version = #{condition.version}</if><if test="condition.isDeleted != null" >and  d.isDeleted = #{condition.isDeleted}</if><if test="condition.createBy != null" >and  d.createBy = #{condition.createBy}</if><if test="condition.updateBy != null" >and  d.updateBy = #{condition.updateBy}</if></trim><include refid="inClause"/></sql><!-- 模糊查询条件 --><sql id="whereLikeClause">where 1=1<trim  suffixOverrides="," >	<if test="condition.id != null" >	    and d.id = #{condition.id}	</if>													 			<if test="condition.focumentImg != null" >and  UPPER(d.focumentImg) LIKE   UPPER(CONCAT(CONCAT('%',#{condition.focumentImg}),'%'))</if><if test="condition.resumeID != null" >and  UPPER(d.resumeID) LIKE   UPPER(CONCAT(CONCAT('%',#{condition.resumeID}),'%'))</if><if test="condition.effective != null" >and  UPPER(d.effective) LIKE   UPPER(CONCAT(CONCAT('%',#{condition.effective}),'%'))</if><if test="condition.documentName != null" >and  UPPER(d.documentName) LIKE   UPPER(CONCAT(CONCAT('%',#{condition.documentName}),'%'))</if><if test="condition.createTime != null" >and  UPPER(d.createTime) LIKE   UPPER(CONCAT(CONCAT('%',#{condition.createTime}),'%'))</if><if test="condition.updateTime != null" >and  UPPER(d.updateTime) LIKE   UPPER(CONCAT(CONCAT('%',#{condition.updateTime}),'%'))</if><if test="condition.version != null" >and  UPPER(d.version) LIKE   UPPER(CONCAT(CONCAT('%',#{condition.version}),'%'))</if><if test="condition.isDeleted != null" >and  UPPER(d.isDeleted) LIKE   UPPER(CONCAT(CONCAT('%',#{condition.isDeleted}),'%'))</if><if test="condition.createBy != null" >and  UPPER(d.createBy) LIKE   UPPER(CONCAT(CONCAT('%',#{condition.createBy}),'%'))</if><if test="condition.updateBy != null" >and  UPPER(d.updateBy) LIKE   UPPER(CONCAT(CONCAT('%',#{condition.updateBy}),'%'))</if></trim><include refid="inClause"/></sql><!-- 插入记录 --><insert id="add"  >  insert into document (id,focumentImg,resumeID,effective,documentName,createTime,updateTime,version,isDeleted,createBy,updateBy)  values(#{id,jdbcType=VARCHAR},#{focumentImg},#{resumeID},#{effective},#{documentName},#{createTime},#{updateTime},#{version},#{isDeleted},#{createBy},#{updateBy})</insert><!-- 修改记录，只修改只不为空的字段 --><update id="update" >	update document set	<trim  suffixOverrides="," >	<if test="focumentImg != null ">focumentImg=#{focumentImg},</if><if test="resumeID != null ">resumeID=#{resumeID},</if><if test="effective != null ">effective=#{effective},</if><if test="documentName != null ">documentName=#{documentName},</if><if test="createTime != null ">createTime=#{createTime},</if><if test="updateTime != null ">updateTime=#{updateTime},</if><if test="version != null ">version=#{version},</if><if test="isDeleted != null ">isDeleted=#{isDeleted},</if><if test="createBy != null ">createBy=#{createBy},</if><if test="updateBy != null ">updateBy=#{updateBy},</if>	</trim> where id=#{id} and version = #{version}-1</update><!-- 删除记录 --><delete id="del" >	delete from document where id = #{id}</delete><!-- 列表总数--><select id="count" resultType="java.lang.Long" >	select count(1) 	from document  d	<include refid="whereClause"/></select><!-- 查询page --><select id="findPage" resultType="Document" >	select 	<include refid="columnList"/>	from document d	<include refid="whereClause"/>	<if test="orderByClause!=null">${orderByClause}</if></select><!-- 模糊查询page --><select id="findLikePage" resultType="Document" >	select 	<include refid="columnList"/>	from document d	<include refid="whereLikeClause"/>	<if test="orderByClause!=null">${orderByClause}</if></select><!-- 查询列表list --><select id="findList" resultMap="DocumentMap" >	select	<include refid="detailList"/>	from  document d	left join attachment attachment on d.focumentImg = attachment.id	<include refid="whereClause"/>	<if test="orderByClause!=null">${orderByClause}</if></select><!--模糊查询list--><select id="findLikeList" resultType="Document" >	select	<include refid="columnList"/>	from document d	<include refid="whereLikeClause"/>	<if test="orderByClause!=null">${orderByClause}</if></select><!-- 查询符合条件的数据的id集合 --><select id="findIds" resultType="String">	select d.${idsColumn}	from document d    <include refid="whereClause"/>    <if test="orderByClause!=null">${orderByClause}</if></select><!-- 查询符合模糊条件的数据的id集合 --><select id="findLikeIds" resultType="String">	select d.${idsColumn}	from document d    <include refid="whereLikeClause"/>    <if test="orderByClause!=null">${orderByClause}</if></select><!-- 获取一个对象通过非id --><select id="one" resultType="Document" >     select    <include refid="columnList"/>     from document d    <include refid="whereClause"/>    <if test="orderByClause!=null">${orderByClause}</if>    limit 0,1</select><!--如果你想返回一个HashMap 就实现这个select标签--><select id="queryHashMap" resultType="java.util.HashMap"  parameterType="Object"></select>	<!--级联查询-->	<sql id="detailList">		d.id as 'id',		d.version as 'version',d.focumentImg as 'focumentImg',d.resumeID as 'resumeID',d.effective as 'effective',d.documentName as 'documentName',		attachment.id as 'attachment.id',		attachment.version as 'attachment.version',attachment.datestr as 'attachment.datestr',attachment.path as 'attachment.path',attachment.name as 'attachment.name',attachment.title as 'attachment.title',attachment.type as 'attachment.type'	</sql>	<!--Attachment映射-->	<resultMap id="AttachmentMap" type="Attachment">		<id property="id" column="attachment.id" />		<result property="version" column="attachment.version" />		<result property="datestr" column="attachment.datestr" />		<result property="path" column="attachment.path" />		<result property="name" column="attachment.name" />		<result property="title" column="attachment.title" />		<result property="type" column="attachment.type" />	</resultMap>	<!--Document映射-->	<resultMap id="DocumentMap" type="Document">		<id property="id" column="id" />		<result property="version" column="version" />		<result property="focumentImg" column="focumentImg" />		<result property="resumeID" column="resumeID" />		<result property="effective" column="effective" />		<result property="documentName" column="documentName" />		<association property="attachment"  javaType="Attachment" resultMap="AttachmentMap"/>	</resultMap>	<!--对象的多级映射-->	<select id="get" resultMap="DocumentMap" parameterType="String">		select		<include refid="detailList"/>		from  document d		left join attachment attachment on d.focumentImg = attachment.id		where  d.id = #{id}  and d.isDeleted = false	</select></mapper>